sra/__init__.py
sra/animal.py
sra/animu.py
sra/canvas.py
sra/chatbot.py
sra/exceptions.py
sra/facts.py
sra/image.py
sra/others.py
sra/pokemon.py
sra/welcome.py
sra_pylib-1.4.2.dist-info/LICENSE
sra_pylib-1.4.2.dist-info/METADATA
sra_pylib-1.4.2.dist-info/WHEEL
sra_pylib-1.4.2.dist-info/top_level.txt
sra_pylib-1.4.2.dist-info/RECORD
