Metadata-Version: 2.1
Name: sra-pylib
Version: 1.4.2
Summary: A Wrapper of some-random-api for Python
Home-page: https://github.com/Sayad-Uddin-Tahsin/sra-pylib
Author: Sayad Uddin Tahsin
Author-email: mr.pluto012@gmail.com
License: MIT
Project-URL: Documentation, https://github.com/Sayad-Uddin-Tahsin/sra-pylib/wiki
Project-URL: Bug Tracker, https://github.com/Sayad-Uddin-Tahsin/sra-pylib/issues
Project-URL: PyPI, https://pypi.org/project/sra-pylib/
Keywords: some-random-api,sra,api-wrapper,sra-pylib,sra-wrapper,tahsin-project
Classifier: Development Status :: 5 - Production/Stable
Classifier: Intended Audience :: Developers
Classifier: License :: OSI Approved :: MIT License
Classifier: Operating System :: OS Independent
Classifier: Programming Language :: Python :: 3.7
Classifier: Programming Language :: Python :: 3.8
Classifier: Programming Language :: Python :: 3.9
Classifier: Programming Language :: Python :: 3.10
Classifier: Programming Language :: Python :: 3.11
Requires-Python: >=3.7
License-File: LICENSE
Requires-Dist: requests (>=2.28.2)
